pymatgraph/Graphics.py
pymatgraph/MatrixBuffer.py
pymatgraph/__init__.py
pymatgraph/backends/__init__.py
pymatgraph/backends/base.py
pymatgraph/backends/kivy_backend.py
pymatgraph/backends/pygame_backend.py
pymatgraph-0.3.1.dist-info/licenses/LICENSE
pymatgraph-0.3.1.dist-info/METADATA
pymatgraph-0.3.1.dist-info/WHEEL
pymatgraph-0.3.1.dist-info/top_level.txt
pymatgraph-0.3.1.dist-info/RECORD
