Metadata-Version: 2.4
Name: pymatgraph
Version: 0.3.1
Summary: A Python package for high-performance tensor-based GPU/CPU buffer rendering, supporting tables, text, images, and graphics.
Author-email: Alec Candidato <aleccandidato@gmail.com>
License-Expression: Apache-2.0
Project-URL: Homepage, https://github.com/0202alcc/pymatgraph
Project-URL: Documentation, https://github.com/0202alcc/pymatgraph#readme
Project-URL: Repository, https://github.com/0202alcc/pymatgraph
Keywords: GPU,CPU,graphics,tensor,rendering,tables,text,images,pygame,kivy,high-performance
Classifier: Development Status :: 4 - Beta
Classifier: Intended Audience :: Developers
Classifier: Topic :: Multimedia :: Graphics
Classifier: Programming Language :: Python :: 3
Classifier: Programming Language :: Python :: 3.8
Classifier: Programming Language :: Python :: 3.9
Classifier: Programming Language :: Python :: 3.10
Classifier: Programming Language :: Python :: 3.11
Classifier: Programming Language :: Python :: 3 :: Only
Classifier: Operating System :: OS Independent
Requires-Python: >=3.8
License-File: LICENSE
Requires-Dist: torch
Requires-Dist: numpy
Requires-Dist: Pillow
Requires-Dist: pygame
Requires-Dist: kivy
Dynamic: license-file
